hybridbackend_tf115_cu121.libs/libasn1-7568bad0.so.8.0.0
hybridbackend_tf115_cu121.libs/libp11-kit-bfb69a48.so.0.3.0
hybridbackend_tf115_cu121.libs/libgnutls-08a81f73.so.30.27.0
hybridbackend_tf115_cu121.libs/libsasl2-d6fe54f7.so.2.0.25
hybridbackend_tf115_cu121.libs/libldap_r-2-041e2314.4.so.2.10.12
hybridbackend_tf115_cu121.libs/libheimntlm-7bf78503.so.0.1.0
hybridbackend_tf115_cu121.libs/libcrypto-6b2af14b.so.1.1
hybridbackend_tf115_cu121.libs/libzstd-9edef536.so.1.4.4
hybridbackend_tf115_cu121.libs/libssh-dc72b09a.so.4.8.4
hybridbackend_tf115_cu121.libs/libnvToolsExt-847d78f2.so.1.0.0
hybridbackend_tf115_cu121.libs/liblber-2-de1aa1fc.4.so.2.10.12
hybridbackend_tf115_cu121.libs/libbrotlicommon-d564b045.so.1.0.7
hybridbackend_tf115_cu121.libs/libhx509-ae29acaa.so.5.0.0
hybridbackend_tf115_cu121.libs/libk5crypto-8b1fbf5a.so.3.1
hybridbackend_tf115_cu121.libs/libbrotlidec-7d8ec2dd.so.1.0.7
hybridbackend_tf115_cu121.libs/libssl-d4a0d08d.so.1.1
hybridbackend_tf115_cu121.libs/libgssapi_krb5-1f5f6419.so.2.2
hybridbackend_tf115_cu121.libs/librtmp-de583d2c.so.1
hybridbackend_tf115_cu121.libs/libsqlite3-b20a3ff9.so.0.8.6
hybridbackend_tf115_cu121.libs/libidn2-db118382.so.0.3.6
hybridbackend_tf115_cu121.libs/liblz4-d6574e34.so.1.9.2
hybridbackend_tf115_cu121.libs/libffi-e49fdd8e.so.7.1.0
hybridbackend_tf115_cu121.libs/libgmp-adce2ea4.so.10.4.0
hybridbackend_tf115_cu121.libs/libcudart-24af1308.so.12.1.55
hybridbackend_tf115_cu121.libs/libnghttp2-35a897be.so.14.19.0
hybridbackend_tf115_cu121.libs/libheimbase-ca98fdee.so.1.0.0
hybridbackend_tf115_cu121.libs/libhcrypto-e4d346a0.so.4.1.0
hybridbackend_tf115_cu121.libs/libhogweed-2148ce14.so.5.0
hybridbackend_tf115_cu121.libs/libkrb5-3935a4c1.so.3.3
hybridbackend_tf115_cu121.libs/libpsl-248a69df.so.5.3.2
hybridbackend_tf115_cu121.libs/libgssapi-db2df496.so.3.0.0
hybridbackend_tf115_cu121.libs/libcom_err-dcfe2569.so.2.1
hybridbackend_tf115_cu121.libs/libwind-fa260d1d.so.0.0.0
hybridbackend_tf115_cu121-1.0.0.dist-info/RECORD
hybridbackend_tf115_cu121-1.0.0.dist-info/top_level.txt
hybridbackend_tf115_cu121-1.0.0.dist-info/WHEEL
hybridbackend_tf115_cu121-1.0.0.dist-info/NOTICE
hybridbackend_tf115_cu121-1.0.0.dist-info/METADATA
hybridbackend_tf115_cu121-1.0.0.dist-info/LICENSE
